kubeseal_auto/cli.py
kubeseal_auto/cluster.py
kubeseal_auto/host.py
kubeseal_auto/kubeseal.py
kubeseal_auto-0.6.0.dist-info/LICENSE
kubeseal_auto-0.6.0.dist-info/METADATA
kubeseal_auto-0.6.0.dist-info/WHEEL
kubeseal_auto-0.6.0.dist-info/entry_points.txt
kubeseal_auto-0.6.0.dist-info/RECORD
