Metadata-Version: 2.3
Name: kubeseal-auto
Version: 0.6.0
Summary: An interactive wrapper for kubeseal binary
License: MIT
Author: Vadim Gedz
Author-email: vadims@linux-tech.io
Requires-Python: >=3.10,<4.0
Classifier: License :: OSI Approved :: MIT License
Classifier: Programming Language :: Python :: 3
Classifier: Programming Language :: Python :: 3.10
Classifier: Programming Language :: Python :: 3.11
Classifier: Programming Language :: Python :: 3.12
Classifier: Programming Language :: Python :: 3.13
Requires-Dist: PyYAML (>=6.0,<7.0)
Requires-Dist: click (>=8.1.7,<9.0.0)
Requires-Dist: colorama (>=0.4.6,<0.5.0)
Requires-Dist: icecream (>=2.1.3,<3.0.0)
Requires-Dist: kubernetes (>=31,<33)
Requires-Dist: questionary (>=2.0.1,<3.0.0)
Requires-Dist: requests (>=2.28.1,<3.0.0)
Project-URL: Homepage, https://github.com/shini4i/kubeseal-auto
Project-URL: Repository, https://github.com/shini4i/kubeseal-auto
